pyhako/__init__.py
pyhako/auth.py
pyhako/client.py
pyhako/credentials.py
pyhako/exceptions.py
pyhako/logging.py
pyhako/manager.py
pyhako/media.py
pyhako/utils.py
pyhako/blog/__init__.py
pyhako/blog/base.py
pyhako/blog/hinatazaka.py
pyhako/blog/nogizaka.py
pyhako/blog/sakurazaka.py
pyhako-0.1.1.dist-info/METADATA
pyhako-0.1.1.dist-info/WHEEL
pyhako-0.1.1.dist-info/RECORD
