Metadata-Version: 2.4
Name: pyhako
Version: 0.1.1
Summary: Async Python client for Sakamichi Group Message API (Nogizaka46, Sakurazaka46, Hinatazaka46)
Project-URL: Homepage, https://github.com/xtorker/PyHako
Project-URL: Repository, https://github.com/xtorker/PyHako
Project-URL: Issues, https://github.com/xtorker/PyHako/issues
Author-email: xtorker <xtorker@gmail.com>
License: MIT
Keywords: api,async,client,hinatazaka46,nogizaka46,sakamichi,sakurazaka46
Classifier: Development Status :: 4 - Beta
Classifier: Intended Audience :: Developers
Classifier: License :: OSI Approved :: MIT License
Classifier: Programming Language :: Python :: 3
Classifier: Programming Language :: Python :: 3.9
Classifier: Programming Language :: Python :: 3.10
Classifier: Programming Language :: Python :: 3.11
Classifier: Programming Language :: Python :: 3.12
Classifier: Topic :: Internet :: WWW/HTTP
Classifier: Topic :: Software Development :: Libraries :: Python Modules
Requires-Python: >=3.9
Requires-Dist: aiofiles>=23.0.0
Requires-Dist: aiohttp>=3.9.0
Requires-Dist: beautifulsoup4>=4.14.3
Requires-Dist: keyring>=24.0.0
Requires-Dist: pillow>=10.0.0
Requires-Dist: playwright>=1.40.0
Requires-Dist: pymediainfo>=6.0.0
Requires-Dist: structlog>=24.1.0
Requires-Dist: tzdata>=2025.3
